s3sync_util/__init__.py
s3sync_util/__main__.py
s3sync_util/__version__.py
s3sync_util/commands/__init__.py
s3sync_util/commands/common.py
s3sync_util/commands/download.py
s3sync_util/commands/multipart.py
s3sync_util/commands/size.py
s3sync_util/commands/state_management.py
s3sync_util/commands/upload.py
s3sync_util/config/__init__.py
s3sync_util/config/utils.py
s3sync_util/main.py
s3sync_util-2.3.2.dist-info/LICENSE
s3sync_util-2.3.2.dist-info/METADATA
s3sync_util-2.3.2.dist-info/WHEEL
s3sync_util-2.3.2.dist-info/entry_points.txt
s3sync_util-2.3.2.dist-info/RECORD
