Metadata-Version: 2.1
Name: s3sync-util
Version: 2.3.2
Summary: Sync directories/files with Amazon S3.
Home-page: https://github.com/GeonsV3Collab/S3SyncUtility
License: MIT
Author: Lakshmi Narasimman
Author-email: lakshminarasimman@v3analytics.in
Requires-Python: >=3.9,<4.0
Classifier: License :: OSI Approved :: MIT License
Classifier: Programming Language :: Python :: 3
Classifier: Programming Language :: Python :: 3.9
Classifier: Programming Language :: Python :: 3.10
Classifier: Programming Language :: Python :: 3.11
Requires-Dist: boto3 (>=1.28.30,<2.0.0)
Requires-Dist: configparser (>=6.0.0,<7.0.0)
Project-URL: Repository, https://github.com/GeonsV3Collab/S3SyncUtility
